zengeld_canvas-0.1.9.dist-info/METADATA
zengeld_canvas-0.1.9.dist-info/WHEEL
zengeld_canvas-0.1.9.dist-info/licenses/LICENSE-APACHE
zengeld_canvas-0.1.9.dist-info/licenses/LICENSE-MIT
zengeld_canvas/__init__.py
zengeld_canvas/zengeld_canvas.cpython-312-darwin.so
zengeld_canvas-0.1.9.dist-info/RECORD
