Metadata-Version: 2.4
Name: zengeld-canvas
Version: 0.1.9
Classifier: Development Status :: 4 - Beta
Classifier: Intended Audience :: Developers
Classifier: Intended Audience :: Financial and Insurance Industry
Classifier: License :: OSI Approved :: MIT License
Classifier: License :: OSI Approved :: Apache Software License
Classifier: Programming Language :: Python :: 3
Classifier: Programming Language :: Python :: 3.8
Classifier: Programming Language :: Python :: 3.9
Classifier: Programming Language :: Python :: 3.10
Classifier: Programming Language :: Python :: 3.11
Classifier: Programming Language :: Python :: 3.12
Classifier: Programming Language :: Rust
Classifier: Topic :: Scientific/Engineering :: Visualization
License-File: LICENSE-MIT
License-File: LICENSE-APACHE
Summary: High-performance SVG chart rendering engine for financial data visualization
Keywords: charts,trading,svg,visualization,finance,candlestick
Author: zengeld
License: MIT OR Apache-2.0
Requires-Python: >=3.8
Project-URL: Homepage, https://github.com/zengeld/zengeld-canvas
Project-URL: Repository, https://github.com/zengeld/zengeld-canvas
Project-URL: Documentation, https://docs.rs/zengeld-canvas
